hatch_bump_version/__init__.py
hatch_bump_version/bump_version_build_hook.py
hatch_bump_version/hooks.py
hatch_bump_version/utils.py
hatch_bump_version-1.0.1.dist-info/METADATA
hatch_bump_version-1.0.1.dist-info/WHEEL
hatch_bump_version-1.0.1.dist-info/entry_points.txt
hatch_bump_version-1.0.1.dist-info/licenses/LICENSE
hatch_bump_version-1.0.1.dist-info/RECORD
