Metadata-Version: 2.4
Name: hatch-bump-version
Version: 1.0.1
Summary: Hatch build hooks plugin for version bumping
Project-URL: Homepage, https://github.com/krokoreit/hatch-bump-version
Project-URL: Source Code, https://github.com/krokoreit/hatch-bump-version
Author-email: krokoreit <krokoreit@gmail.com>
License-Expression: MIT
License-File: LICENSE
Keywords: Python,build hook,bump version,hatch
Classifier: Framework :: Hatch
Classifier: Operating System :: OS Independent
Classifier: Programming Language :: Python :: 3
Requires-Python: >=3.9
Requires-Dist: hatch
Requires-Dist: hatchling
